chroma/__init__.py
chroma/server.py
iflow_mcp_privetin_chroma-0.1.1.dist-info/METADATA
iflow_mcp_privetin_chroma-0.1.1.dist-info/WHEEL
iflow_mcp_privetin_chroma-0.1.1.dist-info/entry_points.txt
iflow_mcp_privetin_chroma-0.1.1.dist-info/licenses/LICENSE
iflow_mcp_privetin_chroma-0.1.1.dist-info/RECORD
