Metadata-Version: 2.4
Name: iflow-mcp_privetin_chroma
Version: 0.1.1
Summary: A MCP server project
Author-email: privetin <81558906+privetin@users.noreply.github.com>
License-File: LICENSE
Requires-Python: >=3.11
Requires-Dist: chromadb>=0.4.22
Requires-Dist: mcp>=1.1.2
Requires-Dist: sentence-transformers>=2.2.2
